README.txt
setup.py
collective/__init__.py
collective.wfform.egg-info/PKG-INFO
collective.wfform.egg-info/SOURCES.txt
collective.wfform.egg-info/dependency_links.txt
collective.wfform.egg-info/entry_points.txt
collective.wfform.egg-info/namespace_packages.txt
collective.wfform.egg-info/not-zip-safe
collective.wfform.egg-info/requires.txt
collective.wfform.egg-info/top_level.txt
collective/wfform/__init__.py
collective/wfform/config.py
collective/wfform/configure.zcml
collective/wfform/interfaces.py
collective/wfform/profiles.zcml
collective/wfform/version.txt
collective/wfform/browser/__init__.py
collective/wfform/browser/configure.zcml
collective/wfform/browser/form.py
collective/wfform/browser/interfaces.py
collective/wfform/browser/javascripts/transitionform.js
collective/wfform/profiles/default/browserlayer.xml
collective/wfform/profiles/default/jsregistry.xml
collective/wfform/profiles/default/metadata.xml
collective/wfform/tests/__init__.py
collective/wfform/tests/base.py
collective/wfform/tests/testMethods.py
collective/wfform/tests/testSetup.py
collective/wfform/tests/utils/__init__.py
collective/wfform/tests/utils/dummy_class.py
collective/wfform/tests/utils/dummy_schema.py
docs/HISTORY.txt
docs/INSTALL.txt
docs/LICENSE.GPL
docs/LICENSE.txt