Metadata-Version: 1.0
Name: collective.wfform
Version: 1.0-a1
Summary: UNKNOWN
Home-page: http://svn.plone.org/svn/collective/
Author: Michael Davis
Author-email: m.r.davis@cranfield.ac.uk
License: GPL
Platform: UNKNOWN
Classifier: Framework :: Plone
Classifier: Programming Language :: Python
